dotenv_tools/__init__.py
dotenv_tools/cli.py
dotenv_tools/core.py
dotenv_tools/expansion.py
dotenv_tools/parser.py
dotenv_tools/setter.py
dotenv_tools/tracker.py
dotenv_tools-0.0.1.dist-info/METADATA
dotenv_tools-0.0.1.dist-info/WHEEL
dotenv_tools-0.0.1.dist-info/entry_points.txt
dotenv_tools-0.0.1.dist-info/licenses/LICENSE
dotenv_tools-0.0.1.dist-info/RECORD
