Metadata-Version: 2.4
Name: dotenv-tools
Version: 0.0.1
Summary: A comprehensive CLI tool to manage environment variables in .env files with complete syntax support
Project-URL: Homepage, https://github.com/LousyBook94/dotenv-tools
Project-URL: Repository, https://github.com/LousyBook94/dotenv-tools
Project-URL: Issues, https://github.com/LousyBook94/dotenv-tools/issues
Author-email: LousyBook01 <lousybook94@gmail.com>
Maintainer-email: LousyBook01 <lousybook94@gmail.com>
License: MIT
License-File: LICENSE
Keywords: cli,dotenv,env,environment,environment-variables
Classifier: Development Status :: 4 - Beta
Classifier: Intended Audience :: Developers
Classifier: License :: OSI Approved :: MIT License
Classifier: Operating System :: OS Independent
Classifier: Programming Language :: Python :: 3
Classifier: Programming Language :: Python :: 3.8
Classifier: Programming Language :: Python :: 3.9
Classifier: Programming Language :: Python :: 3.10
Classifier: Programming Language :: Python :: 3.11
Classifier: Programming Language :: Python :: 3.12
Classifier: Topic :: Software Development :: Libraries :: Python Modules
Classifier: Topic :: System :: Shells
Classifier: Topic :: System :: Systems Administration
Requires-Python: >=3.8
Requires-Dist: click>=8.0.0
Provides-Extra: dev
Requires-Dist: black>=22.0.0; extra == 'dev'
Requires-Dist: build>=0.10.0; extra == 'dev'
Requires-Dist: flake8>=5.0.0; extra == 'dev'
Requires-Dist: pytest-cov>=4.0.0; extra == 'dev'
Requires-Dist: pytest>=7.0.0; extra == 'dev'
Requires-Dist: twine>=4.0.0; extra == 'dev'
